wordly/__init__.py
wordly/__main__.py
wordly/cli.py
wordly/client.py
wordly/parser.py
wordly/status_codes.py
wordly/words.py
wordly-0.3.0.dist-info/licenses/LICENSE
wordly-0.3.0.dist-info/METADATA
wordly-0.3.0.dist-info/WHEEL
wordly-0.3.0.dist-info/entry_points.txt
wordly-0.3.0.dist-info/top_level.txt
wordly-0.3.0.dist-info/RECORD
