Metadata-Version: 2.4
Name: wordly
Version: 0.3.0
Summary: A simple python client that requests dictionary definitions from a server that implements Dictionary Server Protocol
Author-email: Marko Marić <marko@lambdabread.io>
License-Expression: MIT
Project-URL: Homepage, https://markom-dot.github.io/wordly/
Project-URL: Documentation, https://markom-dot.github.io/wordly/
Project-URL: Repository, https://github.com/MarkoM-dot/wordly
Project-URL: Issues, https://github.com/MarkoM-dot/wordly/issues
Project-URL: Changelog, https://github.com/MarkoM-dot/wordly/blob/main/CHANGELOG.md
Keywords: wordly,definition,dictionary,DICT
Classifier: Programming Language :: Python :: 3 :: Only
Classifier: Programming Language :: Python :: 3.11
Classifier: Programming Language :: Python :: 3.12
Classifier: Programming Language :: Python :: 3.13
Classifier: Programming Language :: Python :: 3.14
Classifier: Operating System :: OS Independent
Classifier: Topic :: Software Development :: Libraries
Classifier: Topic :: System :: Networking
Requires-Python: >=3.11
License-File: LICENSE
Provides-Extra: build
Requires-Dist: build; extra == "build"
Requires-Dist: twine; extra == "build"
Dynamic: license-file
